{"Real Estate ID": "0000530", "PIN #": "0695270330", "Location Address": "13065 OLD STAGE RD", "Property Description": "PEGRAM LAND", "Property Owner": "OGBURN, TANDY D", "Owner's Mailing Address": "8730 MOUNT PLEASANT CHURCH RD WILLOW SPRING NC 27592-9761", "Property Location Address": "13065 OLD STAGE RD WILLOW SPRING NC 27592-9485", "Old Map #": "880-00000-0013", "Map/Scale": "0695 01", "VCS": "15WC901", "Fire District": "23", "Township": "PANTHER BRAN", "Land Class": "AGR-FARM", "ETJ": "WC", "Zoning": "R-30", "Acreage": "39.27", "Deed Date": "1/20/2015", "Book & Page": "15895 2516", "Total Units": "2", "Recycle Units": "2", "Heated Area": "3,338", "Total Value Assessed*": "$706,429", "Land Value Assessed": "$509,283", "Bldg. Value Assessed": "$197,146", "Land Use Value": "$93,740", "Use Value Deferment": "$415,543", "Total Deferred Value": "$415,543", "Use/Hist/Tax Relief Assessed": "$290,886"}