{"Real Estate ID": "0000265", "PIN #": "1841711937", "Location Address": "544 E PINE AVE", "Property Description": "LO17 PT OF ALLEN ROGERS", "Property Owner": "GILL, ROBERT C HEIRS", "Owner's Mailing Address": "ROBERT GILL 7904 LIGON MILL RD", "Property Location Address": "544 E PINE AVE WAKE FOREST NC 27587-2632", "Old Map #": "105-00000-0186", "Map/Scale": "1841 19", "VCS": "19WF044", "City": "WAKE FOREST", "Township": "WAKE FOREST", "Land Class": "VACANT", "ETJ": "WF", "Zoning": "UR", "Acreage": ".25", "Deed Date": "1/21/2004", "Book & Page": "00858 0-E-", "Pkg Sale Date": "1/1/1973", "Pkg Sale Price": "$1,000", "Total Units": "0", "Recycle Units": "0", "Total Value Assessed*": "$22,500", "Land Value Assessed": "$22,500"}