{"Real Estate ID": "0000765", "PIN #": "1707303686", "Location Address": "6017 BELLOW ST", "Property Description": "LO26 SOUTH SIX FORKS SE1", "Property Owner": "LILES, KELLY ELIZABETH", "Owner's Mailing Address": "6017 BELLOW ST RALEIGH NC 27609-3615", "Property Location Address": "6017 BELLOW ST RALEIGH NC 27609-3615", "Old Map #": "351-00000-0116", "Map/Scale": "1707 18", "VCS": "07RA015", "City": "RALEIGH", "Township": "HOUSE CREEK", "Land Class": "R-<10-HS", "ETJ": "RA", "Zoning": "R-4", "Acreage": ".26", "Permit Date": "10/7/2020", "Permit #": "0000037859", "Deed Date": "11/24/2020", "Book & Page": "18205 0935", "Revenue Stamps": "770.00", "Pkg Sale Date": "11/24/2020", "Pkg Sale Price": "$385,000", "Total Units": "1", "Recycle Units": "1", "Heated Area": "1,650", "Total Value Assessed*": "$290,410", "Land Value Assessed": "$110,000", "Bldg. Value Assessed": "$180,410"}