{"Real Estate ID": "0000964", "PIN #": "0667994674", "Location Address": "8025 KENSINGTON DR", "Property Description": "LO1 DANIEL & GEORGIA VUNCANNON BM2019-01998", "Property Owner": "HOUGH, BRYAN E & SARA D", "Owner's Mailing Address": "8025 KENSINGTON DR FUQUAY VARINA NC 27526-8807", "Property Location Address": "8025 KENSINGTON DR FUQUAY VARINA NC 27526-8807", "Old Map #": "821--", "Map/Scale": "0667 02", "VCS": "12FV220", "Fire District": "23", "Township": "MIDDLE CREEK", "Land Class": "R-<10-HS", "ETJ": "FV", "Zoning": "RA", "Acreage": "1.77", "Permit Date": "8/29/2019", "Permit #": "0204582019", "Deed Date": "1/6/2020", "Book & Page": "17707 2400", "Revenue Stamps": "1000.00", "Pkg Sale Date": "1/6/2020", "Pkg Sale Price": "$500,000", "Total Units": "1", "Recycle Units": "1", "Heated Area": "3,421", "Total Value Assessed*": "$444,773", "Land Value Assessed": "$110,000", "Bldg. Value Assessed": "$334,773"}