{"Real Estate ID": "0000853", "PIN #": "1707209073", "Location Address": "1021 NORTHCLIFT DR", "Property Description": "LO333 S SIX FORKS PT A SE1", "Property Owner": "HENRY-PENROSE, JOSEPH", "Owner's Mailing Address": "1021 NORTHCLIFT DR RALEIGH NC 27609-3664", "Property Location Address": "1021 NORTHCLIFT DR RALEIGH NC 27609-3664", "Old Map #": "379-00000-0527", "Map/Scale": "1707 18", "VCS": "07RA015", "City": "RALEIGH", "Township": "HOUSE CREEK", "Land Class": "R-<10-HS", "ETJ": "RA", "Zoning": "R-4", "Acreage": ".29", "Permit Date": "5/18/2018", "Permit #": "0000148630", "Deed Date": "6/9/2022", "Book & Page": "19053 1140", "Revenue Stamps": "1000.00", "Pkg Sale Date": "6/9/2022", "Pkg Sale Price": "$500,000", "Total Units": "1", "Recycle Units": "1", "Heated Area": "1,804", "Total Value Assessed*": "$270,820", "Land Value Assessed": "$110,000", "Bldg. Value Assessed": "$160,820"}