{"Real Estate ID": "0000646", "PIN #": "0666085766", "Location Address": "306 CHURCH ST", "Property Description": "LOCHURCH 1 HOUSE & ST", "Property Owner": "CARLYLE, LORI M & PERRY D", "Owner's Mailing Address": "2086 WADE STEPHENSON RD HOLLY SPRINGS NC 27540-8035", "Property Location Address": "306 CHURCH ST FUQUAY VARINA NC 27526-1908", "Old Map #": "119-00000-0060", "Map/Scale": "0666 05", "VCS": "12FV046", "City": "FUQUAY-VARINA", "Township": "MIDDLE CREEK", "Land Class": "R-<10-HS", "ETJ": "FV", "Zoning": "RMD", "Acreage": ".30", "Deed Date": "9/1/2015", "Book & Page": "16138 1969", "Revenue Stamps": "118.00", "Pkg Sale Date": "9/1/2015", "Pkg Sale Price": "$59,000", "Total Units": "1", "Recycle Units": "1", "Heated Area": "1,317", "Total Value Assessed*": "$165,744", "Land Value Assessed": "$55,000", "Bldg. Value Assessed": "$110,744"}