{"Real Estate ID": "0000651", "PIN #": "1714841431", "Location Address": "1217 SOMERSET RD", "Property Description": "LO574 ROLLINGWOOD SE1 BL7", "Property Owner": "ARNOLD, CAROLINE HOLLAND", "Owner's Mailing Address": "1217 SOMERSET RD RALEIGH NC 27610-1136", "Property Location Address": "1217 SOMERSET RD RALEIGH NC 27610-1136", "Old Map #": "525-00000-0640", "Map/Scale": "1714 16", "VCS": "01RA512", "City": "RALEIGH", "Township": "RALEIGH", "Land Class": "R-<10-HS", "ETJ": "RA", "Zoning": "R-6", "Acreage": ".28", "Permit Date": "3/20/1998", "Permit #": "0000038809", "Deed Date": "7/21/2021", "Book & Page": "18608 0500", "Revenue Stamps": "772.00", "Pkg Sale Date": "7/21/2021", "Pkg Sale Price": "$386,000", "Total Units": "1", "Recycle Units": "1", "Heated Area": "1,050", "Total Value Assessed*": "$231,699", "Land Value Assessed": "$115,000", "Bldg. Value Assessed": "$116,699"}