{"Real Estate ID": "0000689", "PIN #": "1706196711", "Location Address": "6037 WINTERGREEN DR", "Property Description": "LO397 NORTHCLIFT SUB SE5", "Property Owner": "GATTER, COURTNEY RHETT", "Owner's Mailing Address": "6037 WINTERGREEN DR RALEIGH NC 27609-3655", "Property Location Address": "6037 WINTERGREEN DR RALEIGH NC 27609-3655", "Old Map #": "379-00000-0642", "Map/Scale": "1706 05", "VCS": "07RA015", "City": "RALEIGH", "Township": "HOUSE CREEK", "Land Class": "R-<10-HS", "ETJ": "RA", "Zoning": "R-4", "Acreage": ".44", "Permit Date": "1/23/2018", "Permit #": "0000146273", "Deed Date": "8/29/2016", "Book & Page": "16511 1715", "Revenue Stamps": "486.00", "Pkg Sale Date": "8/29/2016", "Pkg Sale Price": "$243,000", "Total Units": "1", "Recycle Units": "1", "Heated Area": "2,250", "Total Value Assessed*": "$294,923", "Land Value Assessed": "$110,000", "Bldg. Value Assessed": "$184,923"}