{"Real Estate ID": "0000180", "PIN #": "0795007548", "Location Address": "2104 E CHARLOTTE CT", "Property Description": "LO40 GR PT MEREDITH WDS SUB SE1 BLA", "Property Owner": "FLICK, CONRAD L & VICKIE A FOWLER", "Owner's Mailing Address": "2104 E CHARLOTTE CT RALEIGH NC 27607-3329", "Property Location Address": "2104 E CHARLOTTE CT RALEIGH NC 27607-3329", "Old Map #": "462-00000-0186", "Map/Scale": "0795 17", "VCS": "11RA013", "City": "RALEIGH", "Township": "MEREDITH", "Land Class": "R-<10-HS", "ETJ": "RA", "Zoning": "R-4", "Acreage": ".39", "Permit Date": "4/29/2020", "Permit #": "0000015760", "Deed Date": "11/5/2020", "Book & Page": "18171 2474", "Pkg Sale Date": "12/17/2014", "Pkg Sale Price": "$490,000", "Land Sale Date": "2/27/2014", "Land Sale Price": "$80,000", "Total Units": "1", "Recycle Units": "1", "Heated Area": "3,209", "Total Value Assessed*": "$636,347", "Land Value Assessed": "$120,000", "Bldg. Value Assessed": "$516,347"}