{"Real Estate ID": "0000214", "PIN #": "1713396709", "Location Address": "205 MAPLE ST", "Property Description": "LO307 RCMB EAST COLLEGE PARK BM2018-01676", "Property Owner": "MUTISYA, ELIZABETH B", "Owner's Mailing Address": "205 MAPLE ST RALEIGH NC 27610-2330", "Property Location Address": "205 MAPLE ST RALEIGH NC 27610-2330", "Old Map #": "G003-G0046-0015", "Map/Scale": "1713 06", "VCS": "01RA555", "City": "RALEIGH", "Township": "RALEIGH", "Land Class": "R-<10-HS", "ETJ": "RA", "Zoning": "R-10", "Acreage": ".12", "Permit Date": "12/19/2018", "Permit #": "0000153525", "Deed Date": "6/12/2019", "Book & Page": "17470 2635", "Revenue Stamps": "520.00", "Pkg Sale Date": "6/12/2019", "Pkg Sale Price": "$260,000", "Total Units": "1", "Recycle Units": "1", "Heated Area": "1,590", "Total Value Assessed*": "$384,415", "Land Value Assessed": "$115,000", "Bldg. Value Assessed": "$269,415"}