{"Real Estate ID": "0000327", "PIN #": "1777747310", "Location Address": "7141 HODGE RD", "Property Description": "LO4 RILEY HILL SUB", "Property Owner": "JONES, MARY HELEN HEIRS", "Owner's Mailing Address": "7141 HODGE RD WENDELL NC 27591-9127", "Property Location Address": "7141 HODGE RD WENDELL NC 27591-9127", "Old Map #": "362-00000-0078", "Map/Scale": "1777 04", "VCS": "09WC900", "Fire District": "23", "Township": "LITTLE RIVER", "Land Class": "R-<10-HS", "ETJ": "WC", "Zoning": "R-40W", "Acreage": ".48", "Deed Date": "3/6/2001", "Book & Page": "-E- -", "Total Units": "1", "Recycle Units": "1", "Heated Area": "1,144", "Total Value Assessed*": "$84,644", "Land Value Assessed": "$34,000", "Bldg. Value Assessed": "$50,644"}