{"Real Estate ID": "0000445", "PIN #": "1705306274", "Location Address": "2138 COWPER DR", "Property Description": "PT LTS 1 BLD2&3 BL BM1911-00120", "Property Owner": "DYSART, CHRISTIAN E & GERI L HUGHES", "Owner's Mailing Address": "2138 COWPER DR RALEIGH NC 27608-1324", "Property Location Address": "2138 COWPER DR RALEIGH NC 27608-1324", "Old Map #": "464-00000-0445", "Map/Scale": "1705 18", "VCS": "01RA283", "City": "RALEIGH", "Township": "RALEIGH", "Land Class": "R-<10-HS", "ETJ": "RA", "Zoning": "R-6", "Acreage": ".22", "Permit Date": "12/2/2002", "Permit #": "0000024284", "Deed Date": "4/28/2017", "Book & Page": "16765 0770", "Revenue Stamps": "1540.00", "Pkg Sale Date": "4/28/2017", "Pkg Sale Price": "$770,000", "Total Units": "1", "Recycle Units": "1", "Heated Area": "4,074", "Total Value Assessed*": "$795,611", "Land Value Assessed": "$273,750", "Bldg. Value Assessed": "$521,861"}