{"Real Estate ID": "0000454", "PIN #": "1744146215", "Location Address": "111 SATTERWHITE DR", "Property Description": "LO58 GREEN PINES SUB 3 BM1960-00123", "Property Owner": "JENETTE, AUDREY E", "Owner's Mailing Address": "111 SATTERWHITE DR KNIGHTDALE NC 27545-9503", "Property Location Address": "111 SATTERWHITE DR KNIGHTDALE NC 27545-9503", "Old Map #": "528-00000-0025", "Map/Scale": "1744 03", "VCS": "17KN012", "Fire District": "23", "Township": "ST. MATTHEWS", "Land Class": "R-<10-HS", "ETJ": "KN", "Zoning": "GR3", "Acreage": ".56", "Deed Date": "3/11/2013", "Book & Page": "15178 1999", "Pkg Sale Date": "3/10/1997", "Pkg Sale Price": "$100,000", "Total Units": "1", "Recycle Units": "1", "Heated Area": "1,637", "Total Value Assessed*": "$173,043", "Land Value Assessed": "$42,000", "Bldg. Value Assessed": "$131,043"}