{"Real Estate ID": "0001619", "PIN #": "0753733435", "Location Address": "1203 LOCHCARRON LN", "Property Description": "LO132 GR PT SCOTTISH HILLS SE2", "Property Owner": "WINN, JESSE REAMEY JR & NITA B", "Owner's Mailing Address": "1203 LOCHCARRON LN CARY NC 27511-5143", "Property Location Address": "1203 LOCHCARRON LN CARY NC 27511-5143", "Old Map #": "571-00000-0146", "Map/Scale": "0753 15", "VCS": "04CA125", "City": "CARY", "Township": "CARY", "Land Class": "R-<10-HS", "ETJ": "CA", "Zoning": "R12", "Acreage": ".32", "Permit Date": "5/23/2007", "Permit #": "0000004019", "Deed Date": "1/1/1976", "Book & Page": "02407 0579", "Pkg Sale Date": "1/1/1971", "Pkg Sale Price": "$34,000", "Total Units": "1", "Recycle Units": "1", "Heated Area": "1,713", "Total Value Assessed*": "$284,230", "Land Value Assessed": "$135,000", "Bldg. Value Assessed": "$149,230"}