{"Real Estate ID": "0001033", "PIN #": "1711245848", "Location Address": "1302 W GARNER RD", "Property Description": "LOBRYAN LD", "Property Owner": "PICKARD, LINDA SNOW", "Owner's Mailing Address": "1302 W GARNER RD GARNER NC 27529-3028", "Property Location Address": "1302 W GARNER RD GARNER NC 27529-3028", "Old Map #": "037-00000-0010", "Map/Scale": "1711 14", "VCS": "16GA900", "City": "GARNER", "Township": "ST. MARYS", "Land Class": "R-<10-HS", "ETJ": "GA", "Zoning": "R2", "Acreage": ".79", "Permit Date": "11/26/1997", "Permit #": "0000097817", "Deed Date": "4/9/1999", "Book & Page": "08289 0382", "Revenue Stamps": "3.00", "Pkg Sale Date": "4/9/1999", "Pkg Sale Price": "$1,500", "Total Units": "1", "Recycle Units": "1", "Heated Area": "2,591", "Total Value Assessed*": "$245,012", "Land Value Assessed": "$40,000", "Bldg. Value Assessed": "$205,012"}