{"Real Estate ID": "0001335", "PIN #": "1704679191", "Location Address": "1519 HANOVER ST", "Property Description": "LO67 ROANOKE PARK", "Property Owner": "LEWIS, SHARI ALEXANDRA", "Owner's Mailing Address": "1519 HANOVER ST RALEIGH NC 27608-2535", "Property Location Address": "1519 HANOVER ST RALEIGH NC 27608-2535", "Old Map #": "F013-F0039-0021", "Map/Scale": "1704 11", "VCS": "01RA332", "City": "RALEIGH", "Township": "RALEIGH", "Land Class": "R-<10-HS", "ETJ": "RA", "Zoning": "R-10", "Acreage": ".17", "Permit Date": "1/19/2017", "Permit #": "0000136504", "Deed Date": "6/20/2014", "Book & Page": "15695 2730", "Revenue Stamps": "760.00", "Pkg Sale Date": "6/20/2014", "Pkg Sale Price": "$380,000", "Total Units": "1", "Recycle Units": "1", "Heated Area": "2,334", "Total Value Assessed*": "$615,199", "Land Value Assessed": "$320,000", "Bldg. Value Assessed": "$295,199"}