{"Real Estate ID": "0001062", "PIN #": "1703920658", "Location Address": "1412 GARNER RD", "Property Description": "LO2 & 3 RALEIGH TRACTOR & EQUIPMENT CO BM1946-00087", "Property Owner": "HOKE STREET PH REDEVELOPMENT LLC", "Owner's Mailing Address": "PO BOX 28165 RALEIGH NC 27611-8165", "Property Location Address": "1412 GARNER RD RALEIGH NC 27610-3916", "Old Map #": "579-00000-0120", "Map/Scale": "1703 16", "VCS": "ECRA001", "City": "RALEIGH", "Township": "RALEIGH", "Land Class": "VACANT", "ETJ": "RA", "Zoning": "IX-3", "Acreage": "2.30", "Deed Date": "4/14/2022", "Book & Page": "18992 1820", "Land Sale Date": "2/1/2017", "Land Sale Price": "$450,000", "Total Units": "0", "Recycle Units": "0", "Total Value Assessed*": "$901,692", "Land Value Assessed": "$901,692"}