{"Real Estate ID": "0001654", "PIN #": "1841639123", "Location Address": "412 E JUNIPER AVE", "Property Description": "LO1", "Property Owner": "PORTIER, PAULETTE", "Owner's Mailing Address": "322 BAINBRIDGE ST APT 2A BROOKLYN NY 11233-1930", "Property Location Address": "412 E JUNIPER AVE WAKE FOREST NC 27587-2445", "Old Map #": "105-00000-0048", "Map/Scale": "1841 15", "VCS": "19WF044", "City": "WAKE FOREST", "Township": "WAKE FOREST", "Land Class": "R-<10-HS", "ETJ": "WF", "Zoning": "UR", "Acreage": ".49", "Deed Date": "3/26/2009", "Book & Page": "13450 1442", "Total Units": "1", "Recycle Units": "1", "Heated Area": "1,291", "Total Value Assessed*": "$87,434", "Land Value Assessed": "$27,000", "Bldg. Value Assessed": "$60,434"}