{"Real Estate ID": "0001304", "PIN #": "1711740546", "Location Address": "415 PENNY ST", "Property Description": "BENNETT LAND BM1963-00107", "Property Owner": "ZEKANIS, SCOTT HOWARD & AMANDA", "Owner's Mailing Address": "415 PENNY ST GARNER NC 27529-3219", "Property Location Address": "415 PENNY ST GARNER NC 27529-3219", "Old Map #": "038-00000-0117", "Map/Scale": "1711 15", "VCS": "16GA900", "Fire District": "23", "Township": "ST. MARYS", "Land Class": "R-<10-HS", "ETJ": "GA", "Zoning": "RA", "Acreage": "6.40", "Deed Date": "4/25/2016", "Book & Page": "16362 1714", "Pkg Sale Date": "8/26/2011", "Pkg Sale Price": "$286,000", "Total Units": "1", "Recycle Units": "1", "Heated Area": "2,015", "Total Value Assessed*": "$351,541", "Land Value Assessed": "$200,520", "Bldg. Value Assessed": "$151,021"}